.gitignore
.travis.yml
LICENSE
README.rst
setup.cfg
setup.py
tox.ini
examples/local_reference.py
examples/people.yml
examples/pointers.py
examples/remote_reference.py
examples/yml_string.py
examples/yml_stringio.py
tests/__init__.py
tests/conftest.py
tests/test_api.py
tests/test_proxies.py
tests/test_ref_loaders.py
ymlref/__init__.py
ymlref/api.py
ymlref/proxies.py
ymlref/ref_loaders.py
ymlref.egg-info/PKG-INFO
ymlref.egg-info/SOURCES.txt
ymlref.egg-info/dependency_links.txt
ymlref.egg-info/requires.txt
ymlref.egg-info/top_level.txt