Metadata-Version: 1.0
Name: ymlref
Version: 0.1.1
Summary: ymlref: load Yaml documents with possibility to resolve references.
Home-page: https://github.com/dexter2206/ymlref
Author: Konrad Jałowiecki <dexter2206@gmail.com>
Author-email: dexter2206@gmail.com
License: MIT
Keywords: yml json jsonpointer
Platform: Linux
Platform: Unix
